Metadata-Version: 2.1
Name: f-ask
Version: 1.1.dev0
Summary: A simple framework for building complex web applications.
Home-page: https://www.palletsprojects.com/p/flask/
Author: Armin Ronacher
Author-email: armin.ronacher@active-4.com
Maintainer: Pallets team
Maintainer-email: contact@palletsprojects.com
License: BSD
Project-URL: Documentation, http://flask.pocoo.org/docs/
Project-URL: Code, https://github.com/pallets/flask
Project-URL: Issue tracker, https://github.com/pallets/flask/issues
Platform: any
Classifier: Development Status :: 5 - Production/Stable
Classifier: Environment :: Web Environment
Classifier: Framework :: Flask
Classifier: Intended Audience :: Developers
Classifier: License :: OSI Approved :: BSD License
Classifier: Operating System :: OS Independent
Classifier: Programming Language :: Python
Classifier: Programming Language :: Python :: 2
Classifier: Programming Language :: Python :: 2.7
Classifier: Programming Language :: Python :: 3
Classifier: Programming Language :: Python :: 3.4
Classifier: Programming Language :: Python :: 3.5
Classifier: Programming Language :: Python :: 3.6
Classifier: Programming Language :: Python :: 3.7
Classifier: Topic :: Internet :: WWW/HTTP :: Dynamic Content
Classifier: Topic :: Internet :: WWW/HTTP :: WSGI :: Application
Classifier: Topic :: Software Development :: Libraries :: Application Frameworks
Classifier: Topic :: Software Development :: Libraries :: Python Modules
Requires-Python: >=2.7,!=3.0.*,!=3.1.*,!=3.2.*,!=3.3.*
Requires-Dist: Werkzeug (>=0.14)
Requires-Dist: Jinja2 (>=2.10)
Requires-Dist: itsdangerous (>=0.24)
Requires-Dist: click (>=5.1)
Provides-Extra: dev
Requires-Dist: pytest (>=3) ; extra == 'dev'
Requires-Dist: coverage ; extra == 'dev'
Requires-Dist: tox ; extra == 'dev'
Requires-Dist: sphinx ; extra == 'dev'
Requires-Dist: pallets-sphinx-themes ; extra == 'dev'
Requires-Dist: sphinxcontrib-log-cabinet ; extra == 'dev'
Provides-Extra: docs
Requires-Dist: sphinx ; extra == 'docs'
Requires-Dist: pallets-sphinx-themes ; extra == 'docs'
Requires-Dist: sphinxcontrib-log-cabinet ; extra == 'docs'
Provides-Extra: dotenv
Requires-Dist: python-dotenv ; extra == 'dotenv'
